{
  "type": "attributes",
  "value": {
    "gtin": "gtin",
    "type": "type",
    "level": "level",
    "title": "title",
    "serial": "serial",
    "status": "status",
    "OemGtin": 100,
    "ErrorLamp": false,
    "OemSerial": 200,
    "zoneTitle": "zon title",
    "GearStatus": 100,
    "LightLevel": 100,
    "SurgeCount": 100,
    "groupTitle": "group title",
    "LampFailure": false,
    "LampOnCount": 100,
    "PowerFactor": 100,
    "lampFailure": "lamp failure",
    "ErrorOverall": false,
    "OutputCurrent": 100,
    "OutputVoltage": 100,
    "deviceAddress": "device address",
    "ErrorLampCount": 0,
    "InputFrequency": 100,
    "MaxOutputPower": 100,
    "InputPowerError": "input power error",
    "DriverInputPower": 0,
    "ErrorOvervoltage": false,
    "MainPowerUpCount": 100,
    "ColourTemperature": 100,
    "DriverTemperature": 10,
    "ErrorOverallCount": 0,
    "ErrorUndervoltage": false,
    "LampOperationTime": 420,
    "MaxInputAcVoltage": "maximum input ac voltage",
    "MaximumInputPower": 100,
    "MinInputAcVoltage": "minimun input ac voltage",
    "DriverInputVoltage": 10,
    "ConstantLumenFactor": 10,
    "DriverOperationTime": 10,
    "InitialLuminousFlux": 10,
    "ColourRenderingIndex": 10,
    "ContentFormatVersion": "content format version",
    "DriverMaxTemperature": 100,
    "DriverMinTemperature": 0,
    "ErrorLampOpenCircuit": false,
    "ErrorThermalDerating": false,
    "ErrorLampShortCircuit": false,
    "ErrorOutputPowerLimit": false,
    "ErrorOvervoltageCount": 0,
    "FixtureIdentification": "fixture identification",
    "ErrorUndervoltageCount": 0,
    "DriverEnergyConsumption": 50,
    "ExpectedLifetimeBallast": 80,
    "LampOperationTimeRelativ": 100,
    "ErrorLampOpenCircuitCount": 100,
    "ErrorThermalDeratingCount": 100,
    "DriverMinMarginTemperature": 100,
    "ErrorLampShortCircuitCount": 0,
    "ErrorOutputPowerLimitCount": 0,
    "ExpectedLifetimeLightSource": "expected lifetime lightsource",
    "DriverEnergyConsumptionRelativ": 100,
    "InternalDriverReferenceTemperature": 100
  }
}